CHANGELOG.txt
LICENCE.txt
MANIFEST.in
README.txt
setup.py
textSummarizationLibrary/__init__.py
textSummarizationLibrary.egg-info/PKG-INFO
textSummarizationLibrary.egg-info/SOURCES.txt
textSummarizationLibrary.egg-info/dependency_links.txt
textSummarizationLibrary.egg-info/top_level.txt